stepaudio2.py
stepaudio2vllm.py
token2wav.py
utils.py
cosyvoice2/__init__.py
cosyvoice2/flow/__init__.py
cosyvoice2/flow/decoder_dit.py
cosyvoice2/flow/flow.py
cosyvoice2/flow/flow_matching.py
cosyvoice2/transformer/__init__.py
cosyvoice2/transformer/attention.py
cosyvoice2/transformer/embedding.py
cosyvoice2/transformer/encoder_layer.py
cosyvoice2/transformer/positionwise_feed_forward.py
cosyvoice2/transformer/subsampling.py
cosyvoice2/transformer/upsample_encoder_v2.py
cosyvoice2/utils/class_utils.py
cosyvoice2/utils/common.py
cosyvoice2/utils/mask.py
flashcosyvoice/__init__.py
flashcosyvoice/cli.py
flashcosyvoice/config.py
flashcosyvoice/cosyvoice2.py
flashcosyvoice/cosyvoice3.py
flashcosyvoice/engine/__init__.py
flashcosyvoice/engine/block_manager.py
flashcosyvoice/engine/llm_engine.py
flashcosyvoice/engine/model_runner.py
flashcosyvoice/engine/scheduler.py
flashcosyvoice/engine/sequence.py
flashcosyvoice/modules/__init__.py
flashcosyvoice/modules/flow.py
flashcosyvoice/modules/hifigan.py
flashcosyvoice/modules/qwen2.py
flashcosyvoice/modules/sampler.py
flashcosyvoice/modules/flow_components/__init__.py
flashcosyvoice/modules/flow_components/estimator.py
flashcosyvoice/modules/flow_components/upsample_encoder.py
flashcosyvoice/modules/hifigan_components/__init__.py
flashcosyvoice/modules/hifigan_components/layers.py
flashcosyvoice/modules/qwen2_components/__init__.py
flashcosyvoice/modules/qwen2_components/layers.py
flashcosyvoice/utils/__init__.py
flashcosyvoice/utils/audio.py
flashcosyvoice/utils/context.py
flashcosyvoice/utils/loader.py
flashcosyvoice/utils/memory.py
step_audio2-1.0.0.dist-info/licenses/LICENSE
step_audio2-1.0.0.dist-info/METADATA
step_audio2-1.0.0.dist-info/WHEEL
step_audio2-1.0.0.dist-info/top_level.txt
step_audio2-1.0.0.dist-info/RECORD
