Metadata-Version: 2.4
Name: step-audio2
Version: 1.0.0
Summary: Step-Audio2: Audio understanding and generation model
Author: StepFun AI
License: Apache-2.0
Project-URL: Homepage, https://github.com/stepfun-ai/Step-Audio2
Project-URL: Repository, https://github.com/stepfun-ai/Step-Audio2
Keywords: audio,speech,tts,asr,voice-cloning
Classifier: Development Status :: 4 - Beta
Classifier: Intended Audience :: Developers
Classifier: Intended Audience :: Science/Research
Classifier: License :: OSI Approved :: Apache Software License
Classifier: Programming Language :: Python :: 3
Classifier: Programming Language :: Python :: 3.8
Classifier: Programming Language :: Python :: 3.9
Classifier: Programming Language :: Python :: 3.10
Classifier: Programming Language :: Python :: 3.11
Classifier: Topic :: Scientific/Engineering :: Artificial Intelligence
Classifier: Topic :: Multimedia :: Sound/Audio :: Speech
Requires-Python: >=3.8
License-File: LICENSE
Requires-Dist: torch>=2.0.0
Requires-Dist: transformers>=4.30.0
Requires-Dist: torchaudio>=2.0.0
Requires-Dist: librosa>=0.10.0
Requires-Dist: numpy>=1.20.0
Requires-Dist: onnxruntime>=1.15.0
Requires-Dist: hyperpyyaml>=1.2.0
Requires-Dist: soundfile>=0.12.0
Requires-Dist: s3tokenizer
Provides-Extra: dev
Requires-Dist: pytest>=7.0.0; extra == "dev"
Requires-Dist: black>=23.0.0; extra == "dev"
Requires-Dist: isort>=5.12.0; extra == "dev"
Provides-Extra: web
Requires-Dist: gradio>=4.0.0; extra == "web"
Requires-Dist: requests>=2.28.0; extra == "web"
Dynamic: license-file
